{
  "id": "7000104383",
  "client_id": "a721fe8a-0ffc-4979-b2d0-72112ad68a29",
  "url": "https://static.fanyoy.com/games/citymuti/static6699/mixinen1.html?sec=0&idv=3&locate=en_dmm&pf=mixinen&clientVer=&resVer=2jith4l&codeVer=d5c4085f&channel=mixinen&gv=release&fv=1.0.393&en_dmmVer=nk7e0q&fychannel=mixinen&",
  "name": {
    "ja": "億万長者",
    "en": "Billionaire"
  },
  "text": {
    "ja": [
      "『美女が欲しい？ならば金持ちになれっ！』本格経営SLGが遂に爆誕！『億万長者』！美麗な美女を引き連れて金融戦争を制覇"
    ],
    "en": [
      "Reality simulation, experience the life of being a president, feel the pleasure of earning billions of dollars every minute."
    ]
  },
  "category": "game",
  "tags": {
    "ja": ["ゲーム"],
    "en": ["Game"]
  },
  "language": "en",
  "languages": ["en"],
  "developer": {
    "name": "syx"
  },
  "website": "",
  "support_url": ""
}
